{
  "2010": [
    {
      "id": "summary_1_1",
      "type": "summary",
      "chapter_name": "Haar-Jeet",
      "question": "(क) 'रोज' अथवा 'तिरिछ' कहानी का सारांश लिखिए।",
      "instructions": "किन्ही दो दीर्घ उत्तरीय प्रश्नों के उत्तर दें-"
    },
    {
      "id": "summary_1_2",
      "type": "summary",
      "chapter_name": "Chhappay",
      "question": "'अर्द्धनारीश्वर' या 'ओ सदानीरा पाठ का सारांश लिखिए।",
      "instructions": "किन्ही दो दीर्घ उत्तरीय प्रश्नों के उत्तर दें-"
    },
    {
      "id": "summary_2_1",
      "type": "summary",
      "chapter_name": "Adhinayak",
      "question": "(ख) 'कड़बक' या हार-जीत' कविता का भावार्थ लिखिए।",
      "instructions": "किन्ही दो दीर्घ उत्तरीय प्रश्नों के उत्तर दें-"
    },
    {
      "id": "summary_2_2",
      "type": "summary",
      "chapter_name": "Putra Viyog",
      "question": "'प्यारे नन्हें बेटे को या 'छप्पय पाठ का सारांश लिखिए।",
      "instructions": "किन्ही दो दीर्घ उत्तरीय प्रश्नों के उत्तर दें-"
    }
  ],
  "2013": [
    {
      "id": "summary_1_1",
      "type": "summary",
      "chapter_name": "Tumul Kolahal Kalah Mein",
      "question": "(क) 'रोज' कहानी का सारांश लिखें।",
      "instructions": "किन्हीं दो दीर्घ उत्तरीय प्रश्नों के उत्तर दें-"
    },
    {
      "id": "summary_1_2",
      "type": "summary",
      "chapter_name": "Sipahi Ki Maa",
      "question": "'ओ सदानीरा' पाठ में आए नौका विहार प्रसंग का वर्णन करें।",
      "instructions": "किन्हीं दो दीर्घ उत्तरीय प्रश्नों के उत्तर दें-"
    },
    {
      "id": "summary_2_1",
      "type": "summary",
      "chapter_name": "Kadbak",
      "question": "(ख) 'स्नेहकल कलह' में कविता का भावार्थ लिखें।",
      "instructions": "किन्हीं दो दीर्घ उत्तरीय प्रश्नों के उत्तर दें-"
    },
    {
      "id": "summary_2_2",
      "type": "summary",
      "chapter_name": "Clerk Ki Maut",
      "question": "नारी तो हम हूँ करी, तब ना किया विचार।\nजब जानी तब परिहरि नारी महाविकार।\nउपर्युक्त कविता (पंक्तियों) का भावार्थ अपने शब्दों में लिखें।",
      "instructions": "किन्हीं दो दीर्घ उत्तरीय प्रश्नों के उत्तर दें-"
    }
  ],
  "2015": [
    {
      "id": "summary_1_1",
      "type": "summary",
      "chapter_name": "Kadbak",
      "question": "'पेशगी' कहानी का सारांश लिखें।",
      "instructions": "किन्हीं दो दीर्घ उत्तरीय प्रश्नों के उत्तर दें-"
    },
    {
      "id": "summary_1_2",
      "type": "summary",
      "chapter_name": "Ek Lekh Aur Ek Patra",
      "question": "'हार-जीत' कहानी का सारांश लिखें।",
      "instructions": "किन्हीं दो दीर्घ उत्तरीय प्रश्नों के उत्तर दें-"
    },
    {
      "id": "summary_2_1",
      "type": "summary",
      "chapter_name": "Kavitt",
      "question": "'कड़बक' कविता का भावार्थ लिखें।",
      "instructions": "किन्हीं दो दीर्घ उत्तरीय प्रश्नों के उत्तर दें-"
    },
    {
      "id": "summary_2_2",
      "type": "summary",
      "chapter_name": "Jaan-Jaan Ka Chehra Ek",
      "question": "'गाँव का घर' शीर्षक कविता का सारांश लिखें।",
      "instructions": "किन्हीं दो दीर्घ उत्तरीय प्रश्नों के उत्तर दें-"
    }
  ],
  "2016": [
    {
      "id": "summary_1",
      "type": "summary",
      "chapter_name": "Gaon Ka Ghar",
      "question": "सामाजिक हिंसा सिर्फ राजनीति में ही नहीं, बल्कि सामाजिक संबंधों में भी फैल रही है। इस सामाजिक हिंसा का महिलाएँ सीधे शिकार बनती हैं। साथ में हमारे समाज के तमाम कामगार आदिवासी, छोटे किसान और मजदूर जगह-जगह पर हिंसा को सह रहे हैं। आज यह राजनीति के साथ-साथ राजनीति की मुख्यधारा में भी शामिल हो गयी है, जो भविष्य के लिए अच्छा नहीं है।",
      "instructions": "संक्षेपण करें-"
    },
    {
      "id": "summary_2_1",
      "type": "summary",
      "chapter_name": "Ardhanarishwar",
      "question": "(क) 'छप्पय' कविता का सारांश लिखे।",
      "instructions": "7. निम्नलिखित दो दीर्घ उत्तरीय प्रश्नों के उत्तर दे-"
    },
    {
      "id": "summary_2_2",
      "type": "summary",
      "chapter_name": "Ardhanarishwar",
      "question": "'कड़वक' शीर्षक कविता का सारांश लिखे।",
      "instructions": "अथवा, 7 (क)"
    },
    {
      "id": "summary_3_1",
      "type": "summary",
      "chapter_name": "Roz",
      "question": "(ख) तिरछ' कहानी का सारांश लिखें।",
      "instructions": "7. निम्नलिखित दो दीर्घ उत्तरीय प्रश्नों के उत्तर दे-"
    },
    {
      "id": "summary_3_2",
      "type": "summary",
      "chapter_name": "Shiksha",
      "question": "'शिक्षा' का सारांश लिखें।",
      "instructions": "अथवा, 7 (ख)"
    }
  ],
  "2018": [
    {
      "id": "summary_1_1",
      "type": "summary",
      "chapter_name": "Jaan-Jaan Ka Chehra Ek",
      "question": "भावार्थ लिखें - \nरहिमन वे नर मर चुके जे कहुँ माँग न जाहि। \nउनसे पहले वे मरे जिन मुख निकसत नाहि।।",
      "instructions": "विषयनिष्ठ प्रश्न कुल 25 अंको का होगा।"
    },
    {
      "id": "summary_1_2",
      "type": "summary",
      "chapter_name": "Pad (Tulsidas)",
      "question": "भावार्थ लिखें - \nभू पर नहीं, मनो में हो, बस कही शेष भारत है। \nभारत एक स्वप्न, भू को ऊपर ले जाने वाला, \nभारत एक विचार, स्वर्ग को भू पर लाने वाला।।",
      "instructions": "अथवा"
    },
    {
      "id": "summary_2_1",
      "type": "summary",
      "chapter_name": "Hanste Hue Mera Akelapan",
      "question": "'पंच परमेश्वर' कहानी का सारांश लिखें।",
      "instructions": "विषयनिष्ठ प्रश्न कुल 25 अंको का होगा।"
    },
    {
      "id": "summary_2_2",
      "type": "summary",
      "chapter_name": "Ek Lekh Aur Ek Patra",
      "question": "'जीवन का झरना' कविता का भावार्थ लिखें।",
      "instructions": "अथवा"
    }
  ]
}