[
    {
        "id": "obj_1",
        "type": "objective",
        "question": "Which of the following does not come under archaeology?",
        "prashna": "निम्नलिखित में से कौन सा पुरातत्व के अंतर्गत नहीं आता है?",
        "options": {
            "A": "Inscription",
            "B": "Old temple",
            "C": "Literature",
            "D": "Coins"
        },
        "vikalpa": {
            "A": "अभिलेख",
            "B": "पुराना मंदिर",
            "C": "साहित्य",
            "D": "सिक्के"
        }
    },
    {
        "id": "obj_2",
        "type": "objective",
        "question": "Where has evidence of a ploughed field been found?",
        "prashna": "जुते हुए खेत का साक्ष्य कहाँ मिला है?",
        "options": {
            "A": "Banawali",
            "B": "Kalibangan",
            "C": "Harappa",
            "D": "Shortughai"
        },
        "vikalpa": {
            "A": "बनावली",
            "B": "कालीबंगन",
            "C": "हड़प्पा",
            "D": "शोर्तुघई"
        }
    },
    {
        "id": "obj_3",
        "type": "objective",
        "question": "Which metal was not used by the Indus People?",
        "prashna": "सिंधु निवासी किस धातु का उपयोग नहीं करते थे?",
        "options": {
            "A": "Gold",
            "B": "Silver",
            "C": "Copper",
            "D": "Iron"
        },
        "vikalpa": {
            "A": "सोना",
            "B": "चांदी",
            "C": "तांबा",
            "D": "लोहा"
        }
    },
    {
        "id": "obj_4",
        "type": "objective",
        "question": "Who is refered to as land of seafarer Mesopotamia texts?",
        "prashna": "मेसोपोटामिया के लेख में किसे नाविकों का देश कहा गया है?",
        "options": {
            "A": "Dilmun",
            "B": "Magan",
            "C": "Meluhha",
            "D": "All of these"
        },
        "vikalpa": {
            "A": "दिलमुन",
            "B": "मगान",
            "C": "मेलुहा",
            "D": "इनमें से सभी"
        }
    },
    {
        "id": "obj_5",
        "type": "objective",
        "question": "The longest Harappah inscsibtion contains how may sign?",
        "prashna": "सबसे लंबे हड़प्पा शिलालेख में कितने चिन्ह हैं?",
        "options": {
            "A": "6",
            "B": "12",
            "C": "16",
            "D": "26"
        },
        "vikalpa": {
            "A": "6",
            "B": "12",
            "C": "16",
            "D": "26"
        }
    },
    {
        "id": "obj_6",
        "type": "objective",
        "question": "When did Cunningham report on the Harappah real?",
        "prashna": "हरप्पाई मुहर पर कनिंघम ने कब रिपोर्ट दिया?",
        "options": {
            "A": "1856",
            "B": "1875",
            "C": "1921",
            "D": "1922"
        },
        "vikalpa": {
            "A": "1856",
            "B": "1875",
            "C": "1921",
            "D": "1922"
        }
    },
    {
        "id": "obj_7",
        "type": "objective",
        "question": "Rajagaha (Rajgir) was the capital of which Mahajanpada?",
        "prashna": "राजगाह (राजगीर) किस महाजनपद की राजधानी थी?",
        "options": {
            "A": "Koshala",
            "B": "Panchala",
            "C": "Gandhara",
            "D": "Magadha"
        },
        "vikalpa": {
            "A": "कोशल",
            "B": "पांचाल",
            "C": "गांधार",
            "D": "मगध"
        }
    },
    {
        "id": "obj_8",
        "type": "objective",
        "question": "Who wrote Arthashastra?",
        "prashna": "अर्थशास्त्र किसने लिखा?",
        "options": {
            "A": "Kautilya",
            "B": "Ashoka",
            "C": "Megasthense",
            "D": "Harisena"
        },
        "vikalpa": {
            "A": "कौटिल्य",
            "B": "अशोक",
            "C": "मेगास्थनीज",
            "D": "हरिषेण"
        }
    },
    {
        "id": "obj_9",
        "type": "objective",
        "question": "Who became the Director General of the Archaiological Servey of India in 1944?",
        "prashna": "1944 में भारतीय पुरातात्विक सर्वेक्षण के डायरेक्टर जनरल कौन बने?",
        "options": {
            "A": "John Marshall",
            "B": "R.E.M. Wheeler",
            "C": "Cunningham",
            "D": "S.R.Rao"
        },
        "vikalpa": {
            "A": "जॉन मार्शल",
            "B": "आर.ई.एम. व्हीलर",
            "C": "कनिंघम",
            "D": "एस.आर.राव"
        }
    },
    {
        "id": "obj_10",
        "type": "objective",
        "question": "Who appointed Dhamma mahamatra?",
        "prashna": "धम्म महामात्र की नियुक्ति किसने की?",
        "options": {
            "A": "Ashoka",
            "B": "Ajatashatru",
            "C": "Candragupta Mauraya",
            "D": "Bimbisara"
        },
        "vikalpa": {
            "A": "अशोक",
            "B": "अजातशत्रु",
            "C": "चंद्रगुप्त मौर्य",
            "D": "बिंबिसार"
        }
    },
    {
        "id": "obj_11",
        "type": "objective",
        "question": "Who composed prayaga prashasti?",
        "prashna": "प्रयाग प्रशस्ति की रचना किसने की?",
        "options": {
            "A": "Harisena",
            "B": "Kautilya",
            "C": "Megasthenes",
            "D": "Samudragupta"
        },
        "vikalpa": {
            "A": "हरिषेन",
            "B": "कौटिल्य",
            "C": "मेगास्थनीज",
            "D": "समुद्रगुप्त"
        }
    },
    {
        "id": "obj_12",
        "type": "objective",
        "question": "Who was called Adimai in Tamil Sangam literature?",
        "prashna": "तमिल संगम साहित्य में आणिमई किसे कहा जाता था?",
        "options": {
            "A": "Ploughmen",
            "B": "Peasants",
            "C": "Slaves",
            "D": "Large landowners"
        },
        "vikalpa": {
            "A": "हलवाहा",
            "B": "किसान",
            "C": "दास",
            "D": "बड़े जमींदार"
        }
    },
    {
        "id": "obj_13",
        "type": "objective",
        "question": "Who was called Gahpati in Pali Language?",
        "prashna": "पाली भाषा में गहपति किसे कहा जाता था?",
        "options": {
            "A": "Slaves",
            "B": "Ploughmen",
            "C": "Peasants",
            "D": "None of these"
        },
        "vikalpa": {
            "A": "दास",
            "B": "हलवाहा",
            "C": "किसान",
            "D": "इनमें से कोई नहीं"
        }
    },
    {
        "id": "obj_14",
        "type": "objective",
        "question": "What was the reign of Chandragupta II?",
        "prashna": "चन्द्रगुप्त द्वितीय का शासनकाल क्या था ?",
        "options": {
            "A": "275-315 AD",
            "B": "375-415 AD",
            "C": "335-375 AD",
            "D": "235-275 AD"
        },
        "vikalpa": {
            "A": "275-315 ई",
            "B": "375-415 ई",
            "C": "335-375 ई",
            "D": "235-275 ई"
        }
    },
    {
        "id": "obj_15",
        "type": "objective",
        "question": "Whose daughter was Prabhavati Gupta?",
        "prashna": "प्रभावती गुप्त किसकी पुत्री थी?",
        "options": {
            "A": "Candragupta I",
            "B": "Candragupta II",
            "C": "Samudragupta",
            "D": "Ashoka"
        },
        "vikalpa": {
            "A": "चन्द्रगुप्त प्रथम",
            "B": "चन्द्रगुप्त द्वितीय",
            "C": "समुद्रगुप्त",
            "D": "अशोक"
        }
    },
    {
        "id": "obj_16",
        "type": "objective",
        "question": "When did the Chinese Pilgrim Hien come to India?",
        "prashna": "चीनी तीर्थयात्री फाहियान कब भारत आया?",
        "options": {
            "A": "First century AD",
            "B": "Third century AD",
            "C": "Fifth century AD",
            "D": "Seventh century AD"
        },
        "vikalpa": {
            "A": "पहली शताब्दी ई.पू",
            "B": "तीसरी शताब्दी ई.पू",
            "C": "पाँचवीं शताब्दी ई.पू",
            "D": "सातवीं शताब्दी ई.पू"
        }
    },
    {
        "id": "obj_17",
        "type": "objective",
        "question": "Who was the great philosopher of China?",
        "prashna": "चीन के महान दार्शनिक कौन थे?",
        "options": {
            "A": "Zarathustra",
            "B": "Confucius",
            "C": "Socrates",
            "D": "Aristotle"
        },
        "vikalpa": {
            "A": "जरथुस्त्र",
            "B": "कन्फ्यूशियस",
            "C": "सुकरात",
            "D": "अरस्तू"
        }
    },
    {
        "id": "obj_18",
        "type": "objective",
        "question": "Which god is praised in the Rigved?",
        "prashna": "ऋग्वेद में किस देवता की स्तुति है?",
        "options": {
            "A": "Agni",
            "B": "Indra",
            "C": "Soma",
            "D": "All of these"
        },
        "vikalpa": {
            "A": "अग्नि",
            "B": "इंद्र",
            "C": "सोम",
            "D": "इनमें से सभी"
        }
    },
    {
        "id": "obj_19",
        "type": "objective",
        "question": "Taxila was the capital of which mahajanpada?",
        "prashna": "तक्षशिला किस महाजनपद की राजधानी थी?",
        "options": {
            "A": "Kamboja",
            "B": "Gandhara",
            "C": "Surasena",
            "D": "Panchala"
        },
        "vikalpa": {
            "A": "कंबोज",
            "B": "गांधार",
            "C": "शुरसेन",
            "D": "पांचाल"
        }
    },
    {
        "id": "obj_20",
        "type": "objective",
        "question": "Which metal coins was issued by Yaudheya republic?",
        "prashna": "यौधेय गणराज्य ने किस धातु के सिक्के जारी किये थे?",
        "options": {
            "A": "Gold",
            "B": "Silver",
            "C": "Copper",
            "D": "Iron"
        },
        "vikalpa": {
            "A": "सोना",
            "B": "चांदी",
            "C": "तांबा",
            "D": "लोहा"
        }
    },
    {
        "id": "obj_21",
        "type": "objective",
        "question": "Who first deciphered the Brahmi Inscriptions of Ashoka?",
        "prashna": "अशोक के ब्राह्मी शिलालेखों का अर्थ सर्वप्रथम किसने लगाया?",
        "options": {
            "A": "Colin mackenzie",
            "B": "James Prinsep",
            "C": "Cunningham",
            "D": "Wheeler"
        },
        "vikalpa": {
            "A": "कोलिन मैकेंजी",
            "B": "जेम्स प्रिंसेप",
            "C": "कनिंघम",
            "D": "व्हीलर"
        }
    },
    {
        "id": "obj_22",
        "type": "objective",
        "question": "Inscription of shaka ruler Rudradaman who rebuilt sudarshan lake was written in which language?",
        "prashna": "सुदर्शन झील का पुनर्निर्माण करने वाले शक शासक रुद्रदामन का शिलालेख किस भाषा में लिखा गया था?",
        "options": {
            "A": "Pali",
            "B": "Prakrit",
            "C": "Sanskrit",
            "D": "Tamil"
        },
        "vikalpa": {
            "A": "पाली",
            "B": "प्राकृत",
            "C": "संस्कृत",
            "D": "तमिल"
        }
    },
    {
        "id": "obj_23",
        "type": "objective",
        "question": "What was Buddha's childhood name?",
        "prashna": "बुद्ध के बचपन का नाम क्या था?",
        "options": {
            "A": "Sakya",
            "B": "Gautam",
            "C": "Ananda",
            "D": "Siddhartha"
        },
        "vikalpa": {
            "A": "शाक्य",
            "B": "गौतम",
            "C": "आनंद",
            "D": "सिद्धार्थ"
        }
    },
    {
        "id": "obj_24",
        "type": "objective",
        "question": "Where did Buddha attain enlightenment?",
        "prashna": "बुद्ध को ज्ञान कहाँ प्राप्त हुआ था?",
        "options": {
            "A": "Vaishali",
            "B": "Bodh Gaya",
            "C": "Sarnath",
            "D": "Lumbini"
        },
        "vikalpa": {
            "A": "वैशाली",
            "B": "बोधगया",
            "C": "सारनाथ",
            "D": "लुम्बिनी"
        }
    },
    {
        "id": "obj_25",
        "type": "objective",
        "question": "When was Sanchi stupa discovered?",
        "prashna": "सांची स्तूप की खोज कब हुई?",
        "options": {
            "A": "1774",
            "B": "1784",
            "C": "1818",
            "D": "1854"
        },
        "vikalpa": {
            "A": "1774",
            "B": "1784",
            "C": "1818",
            "D": "1854"
        }
    },
    {
        "id": "obj_26",
        "type": "objective",
        "question": "Who was the 24th tirthankara of Jainism?",
        "prashna": "जैन धर्म के 24वें तीर्थंकर कौन थे?",
        "options": {
            "A": "Parshvanatha",
            "B": "Mahavira",
            "C": "Rishabhdev",
            "D": "Ajitnath"
        },
        "vikalpa": {
            "A": "पार्श्वनाथ",
            "B": "महावीर",
            "C": "ऋषभदेव",
            "D": "अजितनाथ"
        }
    },
    {
        "id": "obj_27",
        "type": "objective",
        "question": "In which language did Al-Biruni write Kitab-ul-hind?",
        "prashna": "अल-बिरूनी ने 'किताब-उल-हिन्द' किस भाषा में लिखी?",
        "options": {
            "A": "Arabi",
            "B": "Persian",
            "C": "Urdu",
            "D": "Hebrew"
        },
        "vikalpa": {
            "A": "अरबी",
            "B": "फारसी",
            "C": "उर्दू",
            "D": "हिब्रू"
        }
    },
    {
        "id": "obj_28",
        "type": "objective",
        "question": "Who appointed Ibn Battuta as the gazi of Delhi?",
        "prashna": "इब्न बतूता को किसने दिल्ली का काजी नियुक्त किया?",
        "options": {
            "A": "Sultan Mahammad",
            "B": "Muhammad Bin Tughlaq",
            "C": "Balban",
            "D": "Akbar"
        },
        "vikalpa": {
            "A": "सुल्तान महम्मूद",
            "B": "मुहम्मद बिन तुगलक",
            "C": "बलबन",
            "D": "अकबर"
        }
    },
    {
        "id": "obj_29",
        "type": "objective",
        "question": "Who was the author of 'Travels in the Mughal Empire'?",
        "prashna": "'ट्रैवल्स इन द मुगल एम्पायर' के लेखक कौन थे?",
        "options": {
            "A": "Roberto Nobili",
            "B": "Barbosa",
            "C": "Tavernier",
            "D": "Francois Bernier"
        },
        "vikalpa": {
            "A": "रॉबर्टो नोबिली",
            "B": "बारबोसा",
            "C": "टैवर्नियर",
            "D": "फ्रांसिस बर्नियर"
        }
    },
    {
        "id": "obj_30",
        "type": "objective",
        "question": "Who among the following European Travelles rettled in India?",
        "prashna": "निम्नलिखित में से कौन यूरोपीय यात्री भारत में ही बस गया ?",
        "options": {
            "A": "Bernier",
            "B": "Tavernier",
            "C": "Manucci",
            "D": "Ibn Battuta"
        },
        "vikalpa": {
            "A": "बर्नियर",
            "B": "टैवर्नियर",
            "C": "मनूची",
            "D": "इब्न बतूता"
        }
    },
    {
        "id": "obj_31",
        "type": "objective",
        "question": "Lord Jagannatha worshipped in Puri, Odisha is a form of which deity?",
        "prashna": "पुरी उड़ीसा में पूजे जाने वाले भगवान जगन्नाथ किस देवता के रुप है?",
        "options": {
            "A": "Brahma",
            "B": "Vishnu",
            "C": "Shiva",
            "D": "None of these"
        },
        "vikalpa": {
            "A": "ब्रह्मा",
            "B": "विष्णु",
            "C": "शिव",
            "D": "इनमें से कोई नहीं"
        }
    },
    {
        "id": "obj_32",
        "type": "objective",
        "question": "Who was warshiped in the tantric worship system?",
        "prashna": "तांत्रिक पूजा पद्धति में किसकी पूजा की जाती थी?",
        "options": {
            "A": "Goddess",
            "B": "Vishnu",
            "C": "Brahma",
            "D": "Kuber"
        },
        "vikalpa": {
            "A": "देवी",
            "B": "विष्णु",
            "C": "ब्रह्मा",
            "D": "कुबेर"
        }
    },
    {
        "id": "obj_33",
        "type": "objective",
        "question": "Who among the following was a women Alvar saint?",
        "prashna": "निम्नलिखित में से कौन स्त्री अलवार संत थी?",
        "options": {
            "A": "Andal",
            "B": "Karaikkal Ammaiyar",
            "C": "Appar",
            "D": "Sundarar"
        },
        "vikalpa": {
            "A": "अंडाल",
            "B": "कराईक्कल अम्मइयार",
            "C": "अप्पार",
            "D": "सुंदरार"
        }
    },
    {
        "id": "obj_34",
        "type": "objective",
        "question": "Which of the following is the composition of Nayanar saints?",
        "prashna": "निम्नलिखित में से कौन नयनार संतों की रचना है?",
        "options": {
            "A": "Nalayira Divyaprabandham",
            "B": "Tevaram",
            "C": "Both (A) and (B)",
            "D": "None of these"
        },
        "vikalpa": {
            "A": "नलयिरा दिव्यप्रबंधम",
            "B": "तवरम",
            "C": "(A) और (B) दोनों",
            "D": "इनमें से कोई नहीं"
        }
    },
    {
        "id": "obj_35",
        "type": "objective",
        "question": "Muslims coming from which country were called Tajika?",
        "prashna": "किस देश से आए हुए मुसलमानों को ताजिका कहा जाता था?",
        "options": {
            "A": "Turkey",
            "B": "Persia",
            "C": "Tajikistan",
            "D": "None of these"
        },
        "vikalpa": {
            "A": "तुर्की",
            "B": "फारस",
            "C": "ताजिकिस्तान",
            "D": "इनमें से कोई नहीं"
        }
    },
    {
        "id": "obj_36",
        "type": "objective",
        "question": "Who among the following was called sultan-ul-Mashaikh?",
        "prashna": "निम्नलिखित में से किसे सुल्तान-उल-मशेख कहा जाता था?",
        "options": {
            "A": "Nizamuddien Auliya",
            "B": "Muinuddin Chishti",
            "C": "Qutubuddin Bakhtiyar kaki",
            "D": "Nasiruddin Chirag-i-Delhi"
        },
        "vikalpa": {
            "A": "निजामुद्दीन औलिया",
            "B": "मुइनुद्दीन चिश्ती",
            "C": "कुतुबुद्दीन बख्तियार काकी",
            "D": "नसीरुद्दीन चिराग-ए-दिल्ली"
        }
    },
    {
        "id": "obj_37",
        "type": "objective",
        "question": "Who described the five symbols of the khalsa Panth?",
        "prashna": "खालसा पंथ के पांच प्रतीकों का वर्णन किसने किया?",
        "options": {
            "A": "Guru Angad",
            "B": "Guru Arjun Dev",
            "C": "Guru Tegh Bahadur",
            "D": "Guru Gobind Singh"
        },
        "vikalpa": {
            "A": "गुरु अंगद",
            "B": "गुरु अर्जुन देव",
            "C": "गुरु तेग बहादुर",
            "D": "गुरु गोबिंद सिंह"
        }
    },
    {
        "id": "obj_38",
        "type": "objective",
        "question": "Whom did Guru Nanak make his successor?",
        "prashna": "गुरु नानक ने किसे अपना उत्तराधिकारी बनाया?",
        "options": {
            "A": "Guru Arjun Dev",
            "B": "Guru Angad",
            "C": "Baba Farid",
            "D": "Guru Tegh Bahadur"
        },
        "vikalpa": {
            "A": "गुरु अर्जुन देव",
            "B": "गुरु अंगद",
            "C": "बाबा फरीद",
            "D": "गुरु तेग बहादुर"
        }
    },
    {
        "id": "obj_39",
        "type": "objective",
        "question": "Who did the final compilication of Guru Granth Sahib?",
        "prashna": "गुरु ग्रंथसाहिब का अंतिम संकलन किसने किया?",
        "options": {
            "A": "Guru Nanak",
            "B": "Guru Angad",
            "C": "Guru Tegh Bahadur",
            "D": "Guru Gobind Singh"
        },
        "vikalpa": {
            "A": "गुरु नानक",
            "B": "गुरु अंगद",
            "C": "गुरु तेग बहादुर",
            "D": "गुरु गोबिंद सिंह"
        }
    },
    {
        "id": "obj_40",
        "type": "objective",
        "question": "When did the Virasshaiva radition emerge in Karnataka?",
        "prashna": "कर्नाटक में वीरशैव परंपरा का उद्भव कब हुआ?",
        "options": {
            "A": "Sixth century",
            "B": "Ninth century",
            "C": "Twelth century",
            "D": "Fourteenth century"
        },
        "vikalpa": {
            "A": "छठी शताब्दी",
            "B": "नवमी शताब्दी",
            "C": "बारहवीं शताब्दी",
            "D": "चौदहवीं शताब्दी"
        }
    },
    {
        "id": "obj_41",
        "type": "objective",
        "question": "When did Harihara Bukka establish the Vijayanagar empire?",
        "prashna": "हरिहर बुक्का ने विजयनगर साम्राज्य की स्थापना कब की?",
        "options": {
            "A": "1330",
            "B": "1333",
            "C": "1336",
            "D": "1353"
        },
        "vikalpa": {
            "A": "1330",
            "B": "1333",
            "C": "1336",
            "D": "1353"
        }
    },
    {
        "id": "obj_42",
        "type": "objective",
        "question": "What was the reign of Saluva dynasty?",
        "prashna": "सुलुव राजवंश का शासनकाल क्या था?",
        "options": {
            "A": "1505-1565",
            "B": "1485-1505",
            "C": "1336-1485",
            "D": "1570-1615"
        },
        "vikalpa": {
            "A": "1505-1565",
            "B": "1485-1505",
            "C": "1336-1485",
            "D": "1570-1615"
        }
    },
    {
        "id": "obj_43",
        "type": "objective",
        "question": "Which dynasty ruled Vijayanagar after the battle of Talikota?",
        "prashna": "तालीकोटा युद्ध के बाद विजयनगर पर किस राजवंश ने शासन किया?",
        "options": {
            "A": "Aravidu",
            "B": "Saluva",
            "C": "Tuluva",
            "D": "Sangama"
        },
        "vikalpa": {
            "A": "अराविदु",
            "B": "सुलुव",
            "C": "तुलुव",
            "D": "संगम"
        }
    },
    {
        "id": "obj_44",
        "type": "objective",
        "question": "Who discovered Hampi?",
        "prashna": "हम्पी की खोज किसने की?",
        "options": {
            "A": "John Marshall",
            "B": "Alexander Greenlaw",
            "C": "Colin Mackenzie",
            "D": "J.F. fleet"
        },
        "vikalpa": {
            "A": "जॉन मार्शल",
            "B": "अलेक्जेंडर ग्रीनलॉ",
            "C": "कॉलिन मैकेन्जी",
            "D": "जे.एफ. फ्लीट"
        }
    },
    {
        "id": "obj_45",
        "type": "objective",
        "question": "When was the Bahmani Kingdom established?",
        "prashna": "बहमनी राज्य की स्थापना कब हुई?",
        "options": {
            "A": "1206",
            "B": "1336",
            "C": "1347",
            "D": "1435"
        },
        "vikalpa": {
            "A": "1206",
            "B": "1336",
            "C": "1347",
            "D": "1435"
        }
    },
    {
        "id": "obj_46",
        "type": "objective",
        "question": "Abdur Razzaq was the ambassador of which country?",
        "prashna": "अब्दुर रज्जाक किस देश का राजदूत था?",
        "options": {
            "A": "Persia",
            "B": "Morocco",
            "C": "Egypt",
            "D": "Portugal"
        },
        "vikalpa": {
            "A": "फारस",
            "B": "मोरक्को",
            "C": "मिस्र",
            "D": "पुर्तगाल"
        }
    },
    {
        "id": "obj_47",
        "type": "objective",
        "question": "What were the kings of Vijayanagar called?",
        "prashna": "विजयनगर के राजाओं को क्या कहा जाता था?",
        "options": {
            "A": "Narapati",
            "B": "Raya",
            "C": "Both (A) and (B)",
            "D": "None of these"
        },
        "vikalpa": {
            "A": "नरपति",
            "B": "राय",
            "C": "(A) और (B) दोनों",
            "D": "इनमें से कोई नही"
        }
    },
    {
        "id": "obj_48",
        "type": "objective",
        "question": "Who was the guardian deity of Vijayanagara?",
        "prashna": "विजयनगर के संरक्षक देवता कौन थे?",
        "options": {
            "A": "Ganesha",
            "B": "Kartikeya",
            "C": "Virupaksha",
            "D": "Vishnu"
        },
        "vikalpa": {
            "A": "गणेश",
            "B": "कार्तिकेय",
            "C": "विरुपाक्ष",
            "D": "विष्णु"
        }
    },
    {
        "id": "obj_49",
        "type": "objective",
        "question": "To which god was the Vitthal Temple of Vijayanagar dedicated?",
        "prashna": "विजयनगर का विट्ठल मंदिर किस देवता को समर्पित था?",
        "options": {
            "A": "Shiva",
            "B": "Brahma",
            "C": "Vishnu",
            "D": "Kubera"
        },
        "vikalpa": {
            "A": "शिव",
            "B": "ब्रह्मा",
            "C": "विष्णु",
            "D": "कुबेर"
        }
    },
    {
        "id": "obj_50",
        "type": "objective",
        "question": "Who wrote ‘Amuktamalyada'?",
        "prashna": "अमुक्तमाल्यद किसने लिखा?",
        "options": {
            "A": "Rama Raya",
            "B": "DevRay I",
            "C": "Krishndev Ray",
            "D": "Basavanna"
        },
        "vikalpa": {
            "A": "राम राय",
            "B": "देवराय प्रथम",
            "C": "कृष्णदेव राय",
            "D": "बसवन्ना"
        }
    },
    {
        "id": "obj_51",
        "type": "objective",
        "question": "Which foreign traveler collectively called the audience hall and the mahanavami dibba as the “House of Victory”?",
        "prashna": "किस विदेशी यात्री ने सभा मंडप तथा महानवमी डिब्बा को संयुक्त रुप से विजय भवन कहा?",
        "options": {
            "A": "Domingo Pais",
            "B": "Fernao Nuniz",
            "C": "Nicolo do Conti",
            "D": "Afanasi Nikitin"
        },
        "vikalpa": {
            "A": "डोमिंगो पेस",
            "B": "फर्नावो नुनिज",
            "C": "निकोलो डो कोंटी",
            "D": "अफानासी निकितिन"
        }
    },
    {
        "id": "obj_52",
        "type": "objective",
        "question": "Akbarnama is divided in how many parts?",
        "prashna": "अकबरनामा कितने खण्डों में विभाजित है?",
        "options": {
            "A": "3",
            "B": "4",
            "C": "5",
            "D": "6"
        },
        "vikalpa": {
            "A": "3",
            "B": "4",
            "C": "5",
            "D": "6"
        }
    },
    {
        "id": "obj_53",
        "type": "objective",
        "question": "Which crop was called Jins-i-Kamil?",
        "prashna": "जिन्स-ए-कामिल किस फसल को कहते थे?",
        "options": {
            "A": "Kharif",
            "B": "Rabi",
            "C": "Cash crops",
            "D": "All of these"
        },
        "vikalpa": {
            "A": "खरीफ",
            "B": "रबी",
            "C": "नकदी फसलें",
            "D": "इनमें से सभी"
        }
    },
    {
        "id": "obj_54",
        "type": "objective",
        "question": "In Maharastra, what was the land gives by farmers to artisans in return for their receives, which becames ancestral, called?",
        "prashna": "महाराष्ट्र में किसानों के द्वारा दस्तकारों को सेवाओं के बदले में दी गई जमीन, जो वंशानुगत हो गई, क्या कहलाती थी?",
        "options": {
            "A": "Miras",
            "B": "Jajmani",
            "C": "Watan",
            "D": "Both A and C"
        },
        "vikalpa": {
            "A": "मीरास",
            "B": "जजमानी",
            "C": "वतन",
            "D": "(A) और (C) दोनो"
        }
    },
    {
        "id": "obj_55",
        "type": "objective",
        "question": "Where did potatoes, tomatoes and tobacco come from in India?",
        "prashna": "भारत में आलू, टमाटर और तम्बाकू कहाँ से आया?",
        "options": {
            "A": "Africa",
            "B": "Europe",
            "C": "Australia",
            "D": "Latien America"
        },
        "vikalpa": {
            "A": "अफ्रीका",
            "B": "यूरोप",
            "C": "ऑस्ट्रेलिया",
            "D": "लैटिन अमेरिका"
        }
    },
    {
        "id": "obj_56",
        "type": "objective",
        "question": "What wrote the Badshahnama?",
        "prashna": "बादशाहनामा किसने लिखा?",
        "options": {
            "A": "Nizamuddin Ahmed",
            "B": "Abdul Hameed Lahori",
            "C": "Faizi",
            "D": "Badayuni"
        },
        "vikalpa": {
            "A": "निजामुद्दीन अहमद",
            "B": "अब्दुल हमीद लाहौरी",
            "C": "फैजी",
            "D": "बदायूँनी"
        }
    },
    {
        "id": "obj_57",
        "type": "objective",
        "question": "Who got Alamgirnama written?",
        "prashna": "आलमगीरनामा किसने लिखवाया?",
        "options": {
            "A": "Aurangzeb",
            "B": "Shahjahan",
            "C": "Jahangir",
            "D": "Babar"
        },
        "vikalpa": {
            "A": "औरंगजेब",
            "B": "शाहजहाँ",
            "C": "जहांगीर",
            "D": "बाबर"
        }
    },
    {
        "id": "obj_58",
        "type": "objective",
        "question": "In which language was Tuzuk-i-Babar composed?",
        "prashna": "तुजुक-ए-बाबरी की रचना किस भाषा में हुई?",
        "options": {
            "A": "Urdu",
            "B": "Turkish",
            "C": "Persian",
            "D": "Punjabi"
        },
        "vikalpa": {
            "A": "उर्दू",
            "B": "तुर्की",
            "C": "फारसी",
            "D": "पंजाबी"
        }
    },
    {
        "id": "obj_59",
        "type": "objective",
        "question": "What is the literal meaning of Sulh-i-Kul?",
        "prashna": "\"सुलह-ए-कुल” का शाब्दिक अर्थ क्या है?",
        "options": {
            "A": "Universal peace",
            "B": "Inheritance",
            "C": "Treaty",
            "D": "Friendship"
        },
        "vikalpa": {
            "A": "सार्वभौमिक शांति",
            "B": "विरासत",
            "C": "संधि",
            "D": "मित्रता"
        }
    },
    {
        "id": "obj_60",
        "type": "objective",
        "question": "When did Babar defeat in the first battle of Panipat in 1526?",
        "prashna": "1526 में पानीपत के प्रथम युद्ध में बाबर ने किसे हराया?",
        "options": {
            "A": "Nadirshah",
            "B": "Ibrahim Lodi",
            "C": "Hemu",
            "D": "Rana sanga"
        },
        "vikalpa": {
            "A": "नादिरशाह",
            "B": "इब्राहिम लोदी",
            "C": "हेमू",
            "D": "राणा सांगा"
        }
    },
    {
        "id": "obj_61",
        "type": "objective",
        "question": "Who was the commander of British forces during the American war of independence who later became Governor General of Bangal?",
        "prashna": "अमेरिकी स्वतंत्रता संग्राम के दौरान ब्रिटिश सेना का कमांडर कौन था, जो बाद में बंगाल का गवर्नर जनरल बना?",
        "options": {
            "A": "Cornwallis",
            "B": "Warren Hastings",
            "C": "Curzon",
            "D": "Bentinck"
        },
        "vikalpa": {
            "A": "कॉर्नवालिस",
            "B": "वॉरेन हेस्टिंग्स",
            "C": "कर्जन",
            "D": "बेंटिक"
        }
    },
    {
        "id": "obj_62",
        "type": "objective",
        "question": "What did the 'Fifth Report' include?",
        "prashna": "'पांचवीं रिपोर्ट' में क्या शामिल था?",
        "options": {
            "A": "Politician of zamindars and ryots",
            "B": "Reports of Collectors",
            "C": "Statistical tables relating to revenue returns",
            "D": "All of these"
        },
        "vikalpa": {
            "A": "जमींदारों और रैयतों का अर्जियाँ",
            "B": "कलेक्टरों की रिपोर्ट",
            "C": "राजस्व विवरणियों से संबंधित सांख्यिकीय तालिकाएँ",
            "D": "उपरोक्त सभी"
        }
    },
    {
        "id": "obj_63",
        "type": "objective",
        "question": "Whose work is 'Anandmath'?",
        "prashna": "'आनंदमठ' किसकी कृति है?",
        "options": {
            "A": "Bankim Chandra",
            "B": "Dayananda",
            "C": "Vivekanand",
            "D": "Keshav Chandra sen"
        },
        "vikalpa": {
            "A": "बंकिम चन्द्र",
            "B": "दयानन्द",
            "C": "विवेकानन्द",
            "D": "केशवचन्द्र सेन"
        }
    },
    {
        "id": "obj_64",
        "type": "objective",
        "question": "Who did the 'Sunset law' apply to?",
        "prashna": "'सूर्यास्त कानून' किस पर लागू था?",
        "options": {
            "A": "Ryat",
            "B": "Zamindar",
            "C": "Moneylender",
            "D": "None of these"
        },
        "vikalpa": {
            "A": "रैयत",
            "B": "जमींदार",
            "C": "साहूकार",
            "D": "इनमें से कोई नही"
        }
    },
    {
        "id": "obj_65",
        "type": "objective",
        "question": "When was 'Damin-i-Koh' demarcated?",
        "prashna": "'दामिन-इ-कोह' का सीमांकन कब हुआ?",
        "options": {
            "A": "1813",
            "B": "1832",
            "C": "1853",
            "D": "1855-56"
        },
        "vikalpa": {
            "A": "1813",
            "B": "1832",
            "C": "1853",
            "D": "1855-56"
        }
    },
    {
        "id": "obj_66",
        "type": "objective",
        "question": "When did the civil war take place in America?",
        "prashna": "अमेरिका में गृहयुद्ध कब हुआ था?",
        "options": {
            "A": "1855",
            "B": "1861",
            "C": "1880",
            "D": "1891"
        },
        "vikalpa": {
            "A": "1855",
            "B": "1861",
            "C": "1880",
            "D": "1891"
        }
    },
    {
        "id": "obj_67",
        "type": "objective",
        "question": "When was the Deccan Riots Commission report enabled in the British Parliament?",
        "prashna": "दक्कन दंगा आयोग की रिपोर्ट ब्रिटिश पार्लियामेंट में कब पेश की गई?",
        "options": {
            "A": "1870",
            "B": "1875",
            "C": "1878",
            "D": "1891"
        },
        "vikalpa": {
            "A": "1870",
            "B": "1875",
            "C": "1878",
            "D": "1891"
        }
    },
    {
        "id": "obj_68",
        "type": "objective",
        "question": "When did Bahadur Shah Zafar take the leadership of revolt of 1857?",
        "prashna": "बहादुर शाह जफर ने 1857 के विद्रोह का नेतृत्व कब किया?",
        "options": {
            "A": "10 may 1857",
            "B": "11 may 1857",
            "C": "20 may 1857",
            "D": "21 may 1857"
        },
        "vikalpa": {
            "A": "10 मई 1857",
            "B": "11 मई 1857",
            "C": "20 मई 1857",
            "D": "21 मई 1857"
        }
    },
    {
        "id": "obj_69",
        "type": "objective",
        "question": "When did the British takes over Awadh by accuring it of misrule?",
        "prashna": "कुशासन का आरोप लगाकर अंग्रेजों ने अवध का अधिग्रहण कब किया?",
        "options": {
            "A": "1801",
            "B": "1805",
            "C": "1851",
            "D": "1856"
        },
        "vikalpa": {
            "A": "1801",
            "B": "1805",
            "C": "1851",
            "D": "1856"
        }
    },
    {
        "id": "obj_70",
        "type": "objective",
        "question": "Who was the Governor General of India at the time of the revolt of 1857?",
        "prashna": "1857 के विद्रोह के समय भारत का गवर्नर जनरल कौन था?",
        "options": {
            "A": "Dalhousie",
            "B": "Wellesley",
            "C": "Canning",
            "D": "Curzon"
        },
        "vikalpa": {
            "A": "डलहौजी",
            "B": "वेलेस्ली",
            "C": "कैनिंग",
            "D": "कर्जन"
        }
    },
    {
        "id": "obj_71",
        "type": "objective",
        "question": "By which Act a provision was made to send Bengal soldiers across the sea?",
        "prashna": "किस अधिनियम द्वारा बंगाल के सिपाहियों को समुद्र पार भेजने की व्यवस्था की गई ?",
        "options": {
            "A": "General Service Enlistment Act of 1856",
            "B": "Doctrine of lapse",
            "C": "Charter act of 1853",
            "D": "None of these"
        },
        "vikalpa": {
            "A": "सामान्य सेवा भर्ती अधिनियम, 1856",
            "B": "व्यपगत का सिद्धांत",
            "C": "1853 का चार्टर अधिनियम",
            "D": "इनमें से कोई नहीं"
        }
    },
    {
        "id": "obj_72",
        "type": "objective",
        "question": "Who was famous as “Danka Shah” in Faizabad during the revolt of 1857?",
        "prashna": "1857 के विद्रोह के समय फैजाबाद में “डंका शाह\" के नाम से कौन विख्यात थे?",
        "options": {
            "A": "Shah Mal",
            "B": "Maulvi Ahmadullah",
            "C": "Wajid Ali shah",
            "D": "Hazart Mahal"
        },
        "vikalpa": {
            "A": "शाहमल",
            "B": "मौलवी अहमदुल्लाह",
            "C": "वाजिद अली शाह",
            "D": "हजरत महल"
        }
    },
    {
        "id": "obj_73",
        "type": "objective",
        "question": "Who among the following was hanged by the British?",
        "prashna": "निम्नलिखित में से किसे अंग्रेजों ने फाँसी पर लटका दिया?",
        "options": {
            "A": "Nana Saheb",
            "B": "Tantiya Tope",
            "C": "Kunwar Singh",
            "D": "Lakshmibai"
        },
        "vikalpa": {
            "A": "नाना साहब",
            "B": "तॉत्या टोपे",
            "C": "कुँवर सिंह",
            "D": "लक्ष्मीबाई"
        }
    },
    {
        "id": "obj_74",
        "type": "objective",
        "question": "Who among the following considered the revolt of 1857 as 'the result of Hindu-Muslim conspiracy'?",
        "prashna": "निम्नलिखित में से किसने 1857 के विद्रोह को 'हिन्दू-मुस्लिम षड़यंत्र का परिणाम' माना?",
        "options": {
            "A": "Reese",
            "B": "James Outram",
            "C": "Holmes",
            "D": "Marx"
        },
        "vikalpa": {
            "A": "रीज",
            "B": "जेम्स आउट्रम",
            "C": "होम्स",
            "D": "मार्क्स"
        }
    },
    {
        "id": "obj_75",
        "type": "objective",
        "question": "What was the immediate cause of the revolt of 1857?",
        "prashna": "1857 के विद्रोह का तात्कालिक कारण क्या था?",
        "options": {
            "A": "Doctrine of lapse",
            "B": "Abolition of Sati System",
            "C": "Propagation of Christianity",
            "D": "Grease cartridges"
        },
        "vikalpa": {
            "A": "व्यपगत का सिद्धांत",
            "B": "सती प्रथा का उन्मूलन",
            "C": "ईसाई धर्म का प्रचार",
            "D": "चर्बी वाले कारतूस"
        }
    },
    {
        "id": "obj_76",
        "type": "objective",
        "question": "Where is the Gateway of India Located?",
        "prashna": "गेटवे ऑफ इंडिया कहाँ स्थित है?",
        "options": {
            "A": "Delhi",
            "B": "Calcutta",
            "C": "Madras",
            "D": "Bombay"
        },
        "vikalpa": {
            "A": "दिल्ली",
            "B": "कलकत्ता",
            "C": "मद्रास",
            "D": "बॉम्बे"
        }
    },
    {
        "id": "obj_77",
        "type": "objective",
        "question": "When was the first attempt made to conduct a census of the whole of India?",
        "prashna": "सम्पूर्ण भारत की जनगणना कराने का पहला प्रयास कब किया गया?",
        "options": {
            "A": "1861",
            "B": "1870",
            "C": "1872",
            "D": "1882"
        },
        "vikalpa": {
            "A": "1861",
            "B": "1870",
            "C": "1872",
            "D": "1882"
        }
    },
    {
        "id": "obj_78",
        "type": "objective",
        "question": "Why was the Survey of India established in 1878?",
        "prashna": "1878 में सर्वे ऑफ इण्डिया की स्थापना क्यों की गई?",
        "options": {
            "A": "To prepare the map",
            "B": "For archaeological exploration",
            "C": "To determine the revenue",
            "D": "For the census"
        },
        "vikalpa": {
            "A": "नक्शा तैयार करने के लिए",
            "B": "पुरातात्विक अन्वेषण के लिए",
            "C": "राजस्व का निर्धारित करने के लिए",
            "D": "जनगणना के लिए"
        }
    },
    {
        "id": "obj_79",
        "type": "objective",
        "question": "Who was Mahatma Gandhi Political Guru?",
        "prashna": "महात्मा गांधी के राजनीतिक गुरु कौन थे?",
        "options": {
            "A": "Lala Lajpat Rai",
            "B": "Dadabhai Naoroji",
            "C": "Gopal Krishna Gokhale",
            "D": "Vivekananda"
        },
        "vikalpa": {
            "A": "लाला लाजपत राय",
            "B": "दादाभाई नौरोजी",
            "C": "गोपाल कृष्ण गोखले",
            "D": "विवेकानन्द"
        }
    },
    {
        "id": "obj_80",
        "type": "objective",
        "question": "Where did Gandhiji establish the Sabarmati Ashram?",
        "prashna": "गाँधीजी ने “साबरमती आश्रम” की स्थापना कहाँ की?",
        "options": {
            "A": "Ahmedabad",
            "B": "Surat",
            "C": "Bombay",
            "D": "Champaran"
        },
        "vikalpa": {
            "A": "अहमदाबाद",
            "B": "सूरत",
            "C": "बम्बई",
            "D": "चम्पारण"
        }
    },
    {
        "id": "obj_81",
        "type": "objective",
        "question": "When was the Lucknow Pact signed between Congress and Muslim League?",
        "prashna": "कांग्रेस और मुस्लिम लीग के बीच लखनऊ पैक्ट कब हुआ?",
        "options": {
            "A": "1906",
            "B": "1911",
            "C": "1916",
            "D": "1917"
        },
        "vikalpa": {
            "A": "1906",
            "B": "1911",
            "C": "1916",
            "D": "1917"
        }
    },
    {
        "id": "obj_82",
        "type": "objective",
        "question": "When did the movement of textile mill workers of Ahmedabad take place?",
        "prashna": "अहमदाबाद के कपड़ा मिल मजदूरों का आंदोलन कब हुआ?",
        "options": {
            "A": "1916",
            "B": "1917",
            "C": "1918",
            "D": "1919"
        },
        "vikalpa": {
            "A": "1916",
            "B": "1917",
            "C": "1918",
            "D": "1919"
        }
    },
    {
        "id": "obj_83",
        "type": "objective",
        "question": "Who was the President of the All India Khilafat conference in Delhi in 1919?",
        "prashna": "1919 में दिल्ली में अखिल भारतीय खिलाफत सम्मेलन के अध्यक्ष कौन थे?",
        "options": {
            "A": "Mohammad ali",
            "B": "Shaukat Ali",
            "C": "Abul kalam Azad",
            "D": "Gandhiji"
        },
        "vikalpa": {
            "A": "मोहम्मद अली",
            "B": "शौकत अली",
            "C": "अबुल कलाम आजाद",
            "D": "गांधीजी"
        }
    },
    {
        "id": "obj_84",
        "type": "objective",
        "question": "When did Gandhi ji start the Non-Cooperation movement?",
        "prashna": "गाँधी जी ने असहयोग आंदोलन कब आरंभ कर दिया?",
        "options": {
            "A": "August 1920",
            "B": "June 1920",
            "C": "September 1920",
            "D": "February 1922"
        },
        "vikalpa": {
            "A": "अगस्त 1920",
            "B": "जून 1920",
            "C": "सितंबर 1920",
            "D": "फरवरी 1922"
        }
    },
    {
        "id": "obj_85",
        "type": "objective",
        "question": "Who among the following was the member of Simon Commission?",
        "prashna": "निम्नलिखित में से कौन साइमन कमीशन के सदस्य थे?",
        "options": {
            "A": "Motilal Nehru",
            "B": "Chittaranjan Das",
            "C": "Gandhiji",
            "D": "None of these"
        },
        "vikalpa": {
            "A": "मोतीलाल नेहरु",
            "B": "चित्तरंजन दास",
            "C": "गाँधीजी",
            "D": "इनमें से कोई नहीं"
        }
    },
    {
        "id": "obj_86",
        "type": "objective",
        "question": "Where was the annual session of the Congress held in December 1929?",
        "prashna": "दिसम्बर 1929 में कांग्रेस का वार्षिक अधिवेशन कहाँ हुआ?",
        "options": {
            "A": "Delhi",
            "B": "Lahore",
            "C": "Calcutta",
            "D": "Bombay"
        },
        "vikalpa": {
            "A": "दिल्ली",
            "B": "लाहौर",
            "C": "कलकत्ता",
            "D": "बम्बई"
        }
    },
    {
        "id": "obj_87",
        "type": "objective",
        "question": "When did the “Gandhiji-Irwin Pact” take place?",
        "prashna": "“गाँधी-इर्विन समझौता” कब हुआ?",
        "options": {
            "A": "January 1931",
            "B": "February 1931",
            "C": "March 1931",
            "D": "April 1931"
        },
        "vikalpa": {
            "A": "जनवरी 1931",
            "B": "फरवरी 1931",
            "C": "मार्च 1931",
            "D": "अप्रैल 1931"
        }
    },
    {
        "id": "obj_88",
        "type": "objective",
        "question": "Where was Rani Gaidinliu, who rebelled against the British, from?",
        "prashna": "अंग्रेजों के विरुद्ध विद्रोह करने वाली रानी गैडिनल्यू कहाँ की थीं?",
        "options": {
            "A": "Manipur",
            "B": "Nagaland",
            "C": "Mizoram",
            "D": "Tripura"
        },
        "vikalpa": {
            "A": "मणिपुर",
            "B": "नागालैंड",
            "C": "मिजोरम",
            "D": "त्रिपुरा"
        }
    },
    {
        "id": "obj_89",
        "type": "objective",
        "question": "When was the communal Awarded?",
        "prashna": "सांप्रदायिक पंचाट की घोषणा कब हुई?",
        "options": {
            "A": "July 1932",
            "B": "August 1932",
            "C": "September 1932",
            "D": "December 1932"
        },
        "vikalpa": {
            "A": "जुलाई 1932",
            "B": "अगस्त 1932",
            "C": "सितंबर 1932",
            "D": "दिसंबर 1932"
        }
    },
    {
        "id": "obj_90",
        "type": "objective",
        "question": "Who presented the “Quit India” resolution while presiding over the Bombay Congress session on 7 August 1942?",
        "prashna": "7 अगस्त 1942 को बंबई कांग्रेस अधिवेशन की अध्यक्षता करते हुए किसने “भारत छोड़ो” प्रस्ताव पेश किया?",
        "options": {
            "A": "Gandhiji",
            "B": "Jawahar lal Nehru",
            "C": "Subhash Chandra Bose",
            "D": "Maulana Abul Kalam Azad"
        },
        "vikalpa": {
            "A": "गाँधीजी",
            "B": "जवाहर लाल नेहरु",
            "C": "सुभाष चन्द्र बोस",
            "D": "मौलाना अबुल कलाम आजाद"
        }
    },
    {
        "id": "obj_91",
        "type": "objective",
        "question": "Where did Subhash Chandra Bose establish the “Provisional Government of Free India” on 21 October 1943?",
        "prashna": "21 अक्टूबर 1943 को सुभाष चन्द्र बोस ने “स्वतंत्र भारत की अस्थायी सरकार” कहाँ स्थापित की?",
        "options": {
            "A": "Singapore",
            "B": "Tokyo",
            "C": "Manipur",
            "D": "Andaman"
        },
        "vikalpa": {
            "A": "सिंगापुर",
            "B": "टोक्यो",
            "C": "मणिपुर",
            "D": "अंडमान"
        }
    },
    {
        "id": "obj_92",
        "type": "objective",
        "question": "Who among the following was not a member of the Cabinet Mission?",
        "prashna": "निम्नलिखित में से कौन कैबिनेट मिशन का सदस्य नहीं था?",
        "options": {
            "A": "Lawrence",
            "B": "Alexander",
            "C": "Cripps",
            "D": "Wavell"
        },
        "vikalpa": {
            "A": "लॉरेंस",
            "B": "अलेक्जेंडर",
            "C": "क्रिप्स",
            "D": "वेवेल"
        }
    },
    {
        "id": "obj_93",
        "type": "objective",
        "question": "When did Clement Attlee announce that British rule would leave India by June 1948?",
        "prashna": "क्लीमेंट एटली ने यह घोषणा कब की कि ब्रिटिश शासन जून 1948 तक भारत छोड़ देगा?",
        "options": {
            "A": "January 1947",
            "B": "February 1947",
            "C": "March 1947",
            "D": "April 1947"
        },
        "vikalpa": {
            "A": "जनवरी 1947",
            "B": "फरवरी 1947",
            "C": "मार्च 1947",
            "D": "अप्रैल 1947"
        }
    },
    {
        "id": "obj_94",
        "type": "objective",
        "question": "The partition of India is the result of which plan of British rule?",
        "prashna": "भारत का विभाजन ब्रिटिश शासन की किस योजना का परिणाम है?",
        "options": {
            "A": "Balkan plan",
            "B": "Wavell plan",
            "C": "Cripps plan",
            "D": "Cabinet Mission plan"
        },
        "vikalpa": {
            "A": "बाल्कन योजना",
            "B": "वैवेल योजना",
            "C": "क्रिप्स योजना",
            "D": "कैबिनेट मिशन योजना"
        }
    },
    {
        "id": "obj_95",
        "type": "objective",
        "question": "Who presided over the first meeting of the constitution Assembly?",
        "prashna": "संविधान सभा की पहली बैठक की अध्यक्षता किसने की?",
        "options": {
            "A": "Dr. Rajendra Prasad",
            "B": "Dr. Sachidanand Sinha",
            "C": "Mahatma Gandhi",
            "D": "Jawahar Lal Nehru"
        },
        "vikalpa": {
            "A": "डॉ. राजेंद्र प्रसाद",
            "B": "डॉ. सच्चिदानंद सिन्हा",
            "C": "महात्मा गांधी",
            "D": "जवाहर लाल नेहरु"
        }
    },
    {
        "id": "obj_96",
        "type": "objective",
        "question": "When was the creation of the Constitution completed?",
        "prashna": "संविधान का निर्माण कब पूरा हुआ?",
        "options": {
            "A": "1945",
            "B": "1946",
            "C": "1947",
            "D": "1949"
        },
        "vikalpa": {
            "A": "1945",
            "B": "1946",
            "C": "1947",
            "D": "1949"
        }
    },
    {
        "id": "obj_97",
        "type": "objective",
        "question": "Who advocated making Hindi the national language in the Constituent Assembly?",
        "prashna": "हिंदी को राष्ट्रभाषा बनाने की वकालत संविधान सभा में किसने की?",
        "options": {
            "A": "Gandhiji",
            "B": "Rajendra Prasad",
            "C": "R.V. Dhulkar",
            "D": "K.M. Munshi"
        },
        "vikalpa": {
            "A": "गाँधीजी",
            "B": "राजेन्द्र प्रसाद",
            "C": "आर.वी. धुलेकर",
            "D": "के.एम. मुंशी"
        }
    },
    {
        "id": "obj_98",
        "type": "objective",
        "question": "Who was the Home Minister in the interim governments?",
        "prashna": "अंतरिम सरकार में गृहमंत्री कौन थे?",
        "options": {
            "A": "B.R. Ambedkar",
            "B": "Jagjivan Ram",
            "C": "Vallabhbhai Patel",
            "D": "Baldev Singh"
        },
        "vikalpa": {
            "A": "बी.आर. अंबेडकर",
            "B": "जगजीवन राम",
            "C": "वल्लभभाई पटेल",
            "D": "बलदेव सिंह"
        }
    },
    {
        "id": "obj_99",
        "type": "objective",
        "question": "Who published the newspapers “New India” and “Commoneweal”?",
        "prashna": "'न्यू इंडिया' और 'कॉमनवील' अखबार किसने प्रकाशित किया?",
        "options": {
            "A": "Tilak",
            "B": "Annie Besant",
            "C": "Gandhiji",
            "D": "Madan Mohan Malaviya"
        },
        "vikalpa": {
            "A": "तिलक",
            "B": "एनी बेसेंट",
            "C": "गाँधीजी",
            "D": "मदन मोहन मालवीय"
        }
    },
    {
        "id": "obj_100",
        "type": "objective",
        "question": "Who was known as “Frontier Gandhi”?",
        "prashna": "\"सीमांत गाँधी\" के रुप में कौन जाने जाते थे?",
        "options": {
            "A": "Abdul Ghaffar Khan",
            "B": "Abul Kalam Azad",
            "C": "K.M. Munshi",
            "D": "Vinoba Bhave"
        },
        "vikalpa": {
            "A": "अब्दुल गफ्फार खान",
            "B": "अबुल कलाम आजाद",
            "C": "के.एम. मुंशी",
            "D": "विनोबा भावे"
        }
    },
    {
        "id": "short_1",
        "type": "short_answer",
        "question": "Write the names of two major sites of Indus Valley Civilization and their excavators.",
        "prashna": "सिंधु घाटी सभ्यता के दो प्रमुख स्थलों और उनके उत्खननकर्ताओं का नाम लिखें।"
    },
    {
        "id": "short_2",
        "type": "short_answer",
        "question": "Write the names of the means used for irrigation in the Indus Valley Civilization.",
        "prashna": "सिंधु घाटी सभ्यता में सिंचाई के लिए उपयोग में लाए जाने वाले साधनों के नाम लिखें।"
    },
    {
        "id": "short_3",
        "type": "short_answer",
        "question": "Write the names of any four major political centres of the Mauryan Empire.",
        "prashna": "मौर्य साम्राज्य के किन्हीं चार प्रमुख राजनीतिक केन्द्रों के नाम लिखें।"
    },
    {
        "id": "short_4",
        "type": "short_answer",
        "question": "Why did Kushana rulers use the title of \"Devaputra\" before their names?",
        "prashna": "कुषाण शासक अपने नाम के आगे 'देवपुत्र' की उपाधि क्यों लगाते थे?"
    },
    {
        "id": "short_5",
        "type": "short_answer",
        "question": "Write the names of any four types of marriages described in Mahabharata.",
        "prashna": "महाभारत में वर्णित विवाह के किन्हीं चार प्रकार के नाम लिखें ।"
    },
    {
        "id": "short_6",
        "type": "short_answer",
        "question": "Mention any two differences between Varna and Caste.",
        "prashna": "वर्ण और जाति में कोई दो अंतर बताऐं।"
    },
    {
        "id": "short_7",
        "type": "short_answer",
        "question": "In which four countries did Buddha's teaching spread?",
        "prashna": "बुद्ध की शिक्षाओं का प्रसार किन चार देशों में हुआ?"
    },
    {
        "id": "short_8",
        "type": "short_answer",
        "question": "How was the Kailashnath temple of Ellora built?",
        "prashna": "एलोरा के कैलाशनाथ मंदिर का निर्माण कैसे हुआ?"
    },
    {
        "id": "short_9",
        "type": "short_answer",
        "question": "Who was Ibn Battuta? During whose reign did he come to India?",
        "prashna": "इब्न बतूता कौन था? वह किसके शासनकाल में भारत आया था?"
    },
    {
        "id": "short_10",
        "type": "short_answer",
        "question": "Why did Al-Biruni write Kitab-ul-Hind?",
        "prashna": "अल-बिरुनी ने किताब-उल-हिन्द क्यों लिखा?"
    },
    {
        "id": "short_11",
        "type": "short_answer",
        "question": "Write the names of any four Nayanar Saints.",
        "prashna": "किन्हीं चार नयनार संतों के नाम लिखें।"
    },
    {
        "id": "short_12",
        "type": "short_answer",
        "question": "Who was Mirabai and whose devotee was she?",
        "prashna": "मीराबाई कौन थी और वह किसकी भक्त थी?"
    },
    {
        "id": "short_13",
        "type": "short_answer",
        "question": "What was the Amar Nayak System?",
        "prashna": "अमर-नायक प्रणाली क्या थी?"
    },
    {
        "id": "short_14",
        "type": "short_answer",
        "question": "Write the names of four foreign travelles who visited Vijayanagara.",
        "prashna": "विजयनगर की यात्रा करने वाले चार विदेशी यात्रियों के नाम लिखें।"
    },
    {
        "id": "short_15",
        "type": "short_answer",
        "question": "What was Rahat(Persian wheel)? How was it useful for farmers?",
        "prashna": "रहत क्या था? यह किसानों के लिए किस प्रकार उपयोगी था?"
    },
    {
        "id": "short_16",
        "type": "short_answer",
        "question": "What was Jins-i-Kamil? Give four examples.",
        "prashna": "जिन्स-ए-कामिल क्या था? चार उदाहरण दें।"
    },
    {
        "id": "short_17",
        "type": "short_answer",
        "question": "Why did Akbar abolish Jizya tax? Write two reasons?",
        "prashna": "अकबर ने जजिया कर क्यों समाप्त किया? दो कारण लिखें?"
    },
    {
        "id": "short_18",
        "type": "short_answer",
        "question": "Whom did Abul Fazl call “Insan-e-Kamil”?",
        "prashna": "अबुल फजल ने किसे “इंसान-ए-कामिल\" कहा था?"
    },
    {
        "id": "short_19",
        "type": "short_answer",
        "question": "Who were the Pahariyas of Rajmahal?",
        "prashna": "राजमहल के पहाड़िया कौन थे?"
    },
    {
        "id": "short_20",
        "type": "short_answer",
        "question": "How did the American Civil War affect Indian Cotton producers?",
        "prashna": "अमेरीकी गृहयुद्ध ने भारत के कपास उत्पादकों को किस प्रकार प्रभावित किया?"
    },
    {
        "id": "short_21",
        "type": "short_answer",
        "question": "What was the immediate cause of the revolt of 1857?",
        "prashna": "1857 के विद्रोह का तात्कालिक कारण क्या था?"
    },
    {
        "id": "short_22",
        "type": "short_answer",
        "question": "Why did Veer Kunwar Singh became famous?",
        "prashna": "वीर कुँवर सिंह क्यों प्रसिद्ध हुए?"
    },
    {
        "id": "short_23",
        "type": "short_answer",
        "question": "Who was Vinodini Dasi?",
        "prashna": "विनोदिनी दासी कौन थी?"
    },
    {
        "id": "short_24",
        "type": "short_answer",
        "question": "Why did Gandhiji start the Camparan movement?",
        "prashna": "गाँधीजी ने चम्पारण आन्दोलन क्यों किया?"
    },
    {
        "id": "short_25",
        "type": "short_answer",
        "question": "Why was the Lahore session of 1929 important?",
        "prashna": "1929 का लाहौर अधिवेशन क्यों महत्वपूर्ण था?"
    },
    {
        "id": "short_26",
        "type": "short_answer",
        "question": "Why did Congress reject the Cripps Proposal?",
        "prashna": "कांग्रेस ने क्रिप्स प्रस्ताव को क्यों ठुकराया?"
    },
    {
        "id": "short_27",
        "type": "short_answer",
        "question": "How was the Azad Hind Fauj Formed?",
        "prashna": "आजाद हिन्द फौज का गठन कैसे हुआ?"
    },
    {
        "id": "short_28",
        "type": "short_answer",
        "question": "Who was Khan Abdul Gaffar Khan?",
        "prashna": "खान अब्दुल गफ्फार खान कौन थे?"
    },
    {
        "id": "short_29",
        "type": "short_answer",
        "question": "Why was the Constitution of India implemented on 26 January 1950?",
        "prashna": "भारत का संविधान 26 जनवरी 1950 को क्यों लागू किया गया?"
    },
    {
        "id": "short_30",
        "type": "short_answer",
        "question": "Why did Jaipal Singh argue for the protection of tribal in the Constituent Assembly? Write two reasons.",
        "prashna": "जयपाल सिंह ने संविधान सभा में आदिवासियों की सुरक्षा के लिए दलील क्यों की? कोई दो कारण लिखें।"
    },
    {
        "id": "long_1",
        "type": "long_answer",
        "question": "Discuss the religious life of the Indus Valley Civilization.",
        "prashna": "सिंधु घाटी सभ्यता के धार्मिक जीवन का विवेचना करें।"
    },
    {
        "id": "long_2",
        "type": "long_answer",
        "question": "Describe the development of Buddist sculpture.",
        "prashna": "बौद्ध मूर्तिकला के विकास का वर्णन करें।"
    },
    {
        "id": "long_3",
        "type": "long_answer",
        "question": "Write a short note on Bhakti movement.",
        "prashna": "भक्ति आंदोलन पर एक संक्षिप्त टिप्पणी लिखें"
    },
    {
        "id": "long_4",
        "type": "long_answer",
        "question": "Describe the central administration of the Mughals.",
        "prashna": "मुगलों के केन्द्रीय प्रशासन का वर्णन करें।"
    },
    {
        "id": "long_5",
        "type": "long_answer",
        "question": "Throw light on the causes and nature of santhal revolt.",
        "prashna": "संथाल विद्रोह के कारण और स्वरुप पर प्रकाश डालें।"
    },
    {
        "id": "long_6",
        "type": "long_answer",
        "question": "What were the results of the revolt of 1857? How did it develop nationalism?",
        "prashna": "1857 के विद्रोह का क्या परिणाम हुआ? इसने राष्ट्रवाद को कैसे विकसित किया?"
    },
    {
        "id": "long_7",
        "type": "long_answer",
        "question": "Evaluate the role of Gandhiji in the Indian freedom movement.",
        "prashna": "भारतीय स्वतंत्रता आंदोलन में गाँधीजी की भूमिका का मूल्यांकन करें।"
    },
    {
        "id": "long_8",
        "type": "long_answer",
        "question": "How did the Constituent Assembly resolve the question of language controversy?",
        "prashna": "संविधान सभा ने भाषा-विवाद के प्रश्न को कैसे सुलझाया?"
    }
]