{
  "2021": [
    {
      "id": "long_1",
      "type": "long_answer",
      "chapter_name": "Theory of Consumer Behaviour",
      "question": "Explain consumer equilibrium with the help of indifference curve and budget line.",
      "prashna": "अनधिमान वक्र एवं बजट रेखा की सहायता से उपभोक्ता संतुलन को स्पष्ट करें।"
    },
    {
      "id": "long_2",
      "type": "long_answer",
      "chapter_name": "Theory of Consumer Behaviour",
      "question": "Explain elastic, inelastic and unitary elastic demand with the help of diagrams.",
      "prashna": "लोचदार, लोचहीन एवं इकाई लोच की माँग की चित्र की सहायता से व्याख्या करें।"
    },
    {
      "id": "long_3",
      "type": "long_answer",
      "chapter_name": "The Theory of the Firm under Perfect Competition",
      "question": "What are the characteristics of a perfectly competitive market?",
      "prashna": "एक पूर्ण प्रतिस्पर्धी बाजार के क्या लक्षण हैं?"
    },
    {
      "id": "long_4",
      "type": "long_answer",
      "chapter_name": "The Theory of the Firm under Perfect Competition",
      "question": "What are the determinants of the supply curve of a firm?",
      "prashna": "फर्म की पूर्ति वक्र के निर्धारक तत्व कौन-कौन से हैं?"
    },
    {
      "id": "long_5",
      "type": "long_answer",
      "chapter_name": "National Income Accounting",
      "question": "How does inequality in the distribution of Gross Domestic Product affect economic welfare?",
      "prashna": "सकल घरेलू उत्पाद के वितरण में विषमता आर्थिक कल्याण को कैसे प्रभावित करता है?"
    },
    {
      "id": "long_6",
      "type": "long_answer",
      "chapter_name": "Money and Banking",
      "question": "What are the main functions of money? Explain.",
      "prashna": "मुद्रा के प्रमुख कार्य क्या हैं? समझाइए।"
    },
    {
      "id": "long_7",
      "type": "long_answer",
      "chapter_name": "Money and Banking",
      "question": "How does a commercial bank create credit? Explain with an example.",
      "prashna": "व्यावसायिक बैंक किस प्रकार साख का निर्माण करती है? उदाहरण के साथ समझायें।"
    },
    {
      "id": "long_8",
      "type": "long_answer",
      "chapter_name": "Government Budget and the Economy",
      "question": "The government needs loans to meet the fiscal deficit. Explain.",
      "prashna": "राजकोषीय घाटा को पूरा करने के लिए सरकार को ऋण की आवश्यकता पड़ती है। व्याख्या कीजिए।"
    }
  ],
  "2022": [
    {
      "id": "long_1",
      "type": "long_answer",
      "chapter_name": "Introduction: Microeconomics",
      "question": "Economics is both positive and normative science. Explain.",
      "prashna": "अर्थशास्त्र वास्तविक और आदर्शात्मक विज्ञान दोनों है। समझाइए |"
    },
    {
      "id": "long_2",
      "type": "long_answer",
      "chapter_name": "Introduction: Microeconomics",
      "question": "What is an economic problem? Why does it arise?",
      "prashna": "आर्थिक समस्या क्या है ? यह क्यों उत्पन्न होती है ?"
    },
    {
      "id": "long_3",
      "type": "long_answer",
      "chapter_name": "Theory of Consumer Behaviour",
      "question": "Why does demand curve slope downward from left to right?",
      "prashna": "माँग वक्र बायें से दायें नीचे क्यों गिरता है ?"
    },
    {
      "id": "long_4",
      "type": "long_answer",
      "chapter_name": "Non-competitive Markets",
      "question": "How is price determined under monopoly market?",
      "prashna": "एकाधिकार बाजार में मूल्य निर्धारण कैसे होता है?"
    },
    {
      "id": "long_5",
      "type": "long_answer",
      "chapter_name": "National Income Accounting",
      "question": "How is national income estimated by value added method?",
      "prashna": "मूल्य वृद्धि विधि द्वारा राष्ट्रीय आय की गणना कैसे की जाती है?"
    },
    {
      "id": "long_6",
      "type": "long_answer",
      "chapter_name": "Money and Banking",
      "question": "What is Barter system? Mention its difficulties.",
      "prashna": "वस्तु विनिमय प्रणाली क्या है? इसकी कठिनाइयाँ बताइए।"
    },
    {
      "id": "long_7",
      "type": "long_answer",
      "chapter_name": "Money and Banking",
      "question": "Explain briefly the primary functions of a commercial bank.",
      "prashna": "एक व्यावसायिक बैंक के मुख्य कार्यों का संक्षिप्त वर्णन कीजिए।"
    },
    {
      "id": "long_8",
      "type": "long_answer",
      "chapter_name": "Government Budget and the Economy",
      "question": "What is meant by Budget? What are the objectives of budget?",
      "prashna": "बजट से आप क्या समझते हैं ? बजट के क्या उद्देश्य हैं ?"
    }
  ],
  "2023": [
    {
      "id": "long_1",
      "type": "long_answer",
      "chapter_name": "Introduction: Macroeconomics",
      "question": "What is the difference between Microeconomics and Macroeconomics?",
      "prashna": "व्यष्टि अर्थशास्त्र और समष्टि अर्थशास्त्र में क्या अन्तर है ?"
    },
    {
      "id": "long_2",
      "type": "long_answer",
      "chapter_name": "The Theory of the Firm under Perfect Competition",
      "question": "Explain Total Revenue, Average Revenue, and Marginal Revenue.",
      "prashna": "कुल आगम, औसत आगम और सीमान्त आगम की व्याख्या कीजिए।"
    },
    {
      "id": "long_3",
      "type": "long_answer",
      "chapter_name": "Theory of Consumer Behaviour",
      "question": "What is Demand? Explain the determinants of Demand.",
      "prashna": "माँग क्या है ? माँग के निर्धारक तत्वों को समझाइए ।"
    },
    {
      "id": "long_4",
      "type": "long_answer",
      "chapter_name": "National Income Accounting",
      "question": "Explain the circular flow of income in a two-sector economy.",
      "prashna": "एक द्वि-क्षेत्रीय अर्थव्यवस्था में आय का चक्रीय प्रवाह समझाइए।"
    },
    {
      "id": "long_5",
      "type": "long_answer",
      "chapter_name": "The Theory of the Firm under Perfect Competition",
      "question": "What is Perfect Competition? State the features of Perfect Competition.",
      "prashna": "पूर्ण प्रतियोगिता क्या है ? पूर्ण प्रतियोगिता की विशेषताएँ बताइए।"
    },
    {
      "id": "long_6",
      "type": "long_answer",
      "chapter_name": "Determination of Income and Employment",
      "question": "What is Excess Demand? What is its effect on output and prices?",
      "prashna": "अतिरेक माँग क्या है ? उत्पाद और कीमतों पर इसका क्या प्रभाव होता है ?"
    },
    {
      "id": "long_7",
      "type": "long_answer",
      "chapter_name": "Money and Banking",
      "question": "What are the instruments of Monetary Policy of the Reserve Bank of India?",
      "prashna": "भारतीय रिजर्व बैंक की मौद्रिक नीति के कौन-कौन से उपकरण हैं ?"
    },
    {
      "id": "long_8",
      "type": "long_answer",
      "chapter_name": "Open Economy Macroeconomics",
      "question": "Describe the merits and demerits of a flexible exchange rate system.",
      "prashna": "लोचशील विनिमय दर प्रणाली के गुण तथा दोषों का वर्णन करें।"
    }
  ],
  "2024": [
    {
      "id": "long_1",
      "type": "long_answer",
      "chapter_name": "National Income Accounting",
      "question": "Does increase in gross domestic product show an improvement in public welfare ? Explain.",
      "prashna": "क्या सकल घरेलू उत्पाद में वृद्धि जन कल्याण में सुधार को दर्शाता है ? व्याख्या करें।"
    },
    {
      "id": "long_2",
      "type": "long_answer",
      "chapter_name": "Money and Banking",
      "question": "What are the important functions of money ? Write with examples.",
      "prashna": "मुद्रा के प्रमुख कार्य क्या-क्या हैं ? उदाहरण के साथ लिखें।"
    },
    {
      "id": "long_3",
      "type": "long_answer",
      "chapter_name": "Determination of Income and Employment",
      "question": "Explain paradox of thrift.",
      "prashna": "मितव्ययिता के विरोधाभास की व्याख्या कीजिए।"
    },
    {
      "id": "long_4",
      "type": "long_answer",
      "chapter_name": "Government Budget and the Economy",
      "question": "What is the relationship between government deficit and government debt ? Explain.",
      "prashna": "सरकारी घाटे और सरकारी ऋण में क्या संबंध है ? व्याख्या कीजिए।"
    },
    {
      "id": "long_5",
      "type": "long_answer",
      "chapter_name": "Theory of Consumer Behaviour",
      "question": "Show consumer's equilibrium with the help of indifference curve.",
      "prashna": "अनधिमान वक्र के द्वारा उपभोक्ता संतुलन को दर्शायें।"
    },
    {
      "id": "long_6",
      "type": "long_answer",
      "chapter_name": "Production and Costs",
      "question": "Show total cost, marginal cost and average cost with the help of diagrams.",
      "prashna": "कुल लागत, सीमांत लागत एवं औसत लागत को चित्रों द्वारा दर्शायें।"
    },
    {
      "id": "long_7",
      "type": "long_answer",
      "chapter_name": "The Theory of the Firm under Perfect Competition",
      "question": "Clarify profit maximization of a competitive firm with the help of diagram.",
      "prashna": "एक प्रतिस्पर्द्धी फर्म के लाभ अधिकतमीकरण को चित्र द्वारा स्पष्ट करें।"
    },
    {
      "id": "long_8",
      "type": "long_answer",
      "chapter_name": "Market Equilibrium",
      "question": "Show the minimum support price policy with the help of diagram.",
      "prashna": "निम्नतम निर्धारित कीमत की नीति को चित्र द्वारा दर्शायें।"
    }
  ],
  "2025": [
    {
      "id": "long_1",
      "type": "long_answer",
      "chapter_name": "Theory of Consumer Behaviour",
      "question": "What are the exception of Law of Demand? Explain",
      "prashna": "मांग के नियम के क्या अपवाद है? समझाए।"
    },
    {
      "id": "long_2",
      "type": "long_answer",
      "chapter_name": "Theory of Consumer Behaviour",
      "question": "Explain the factors determining elasticity of demand.",
      "prashna": "मांग की लोच को प्रभावित करने वाले तत्वों की व्याख्या कीजिए।"
    },
    {
      "id": "long_3",
      "type": "long_answer",
      "chapter_name": "Production and Costs",
      "question": "Distinguish difference between fixed and variable cost.",
      "prashna": "स्थिर एवं परिवर्तनशील लागत में अंतर स्पष्ट कीजिए।"
    },
    {
      "id": "long_4",
      "type": "long_answer",
      "chapter_name": "The Theory of the Firm under Perfect Competition",
      "question": "Explain the methods of measuring elasticity of Supply.",
      "prashna": "पूर्ति की लोच मापने की विधियाँ समझाए।"
    },
    {
      "id": "long_5",
      "type": "long_answer",
      "chapter_name": "Market Equilibrium",
      "question": "Explain the relationship between market price and normal price.",
      "prashna": "बाजार मूल्य एवं सामान्य मूल्य में परस्पर सम्बन्ध स्पष्ट कीजिए।"
    },
    {
      "id": "long_6",
      "type": "long_answer",
      "chapter_name": "Money and Banking",
      "question": "Explain the main functions of Reserve Bank of India.",
      "prashna": "भारतीय रिजर्व बैंक के मुख्य कार्यों का वर्णन करें।"
    },
    {
      "id": "long_7",
      "type": "long_answer",
      "chapter_name": "Government Budget and the Economy",
      "question": "State the objectives of Government Budget.",
      "prashna": "सरकारी बजट के उद्देश्यों को बताइए।"
    },
    {
      "id": "long_8",
      "type": "long_answer",
      "chapter_name": "Open Economy Macroeconomics",
      "question": "Explain the meaning of deficit in balance of payment.",
      "prashna": "भुगतान शेष में घाटे के अभिप्राय को स्पष्ट कीजिए।"
    }
  ],
  "2026": [
    {
      "id": "long_1",
      "type": "long_answer",
      "chapter_name": "Theory of Consumer Behaviour",
      "question": "Explain consumer equilibrium through indifference curve.",
      "prashna": "अनधिमान वक्र के द्वारा उपभोक्ता के संतुलन की सचित्र व्याख्या करें।"
    },
    {
      "id": "long_2",
      "type": "long_answer",
      "chapter_name": "Theory of Consumer Behaviour",
      "question": "Define price elasticity of demand. Draw demand curves with price elasticity of demand $|e_d| = 0$, $|e_d| = 1$ and $|e_d| = \\infty$.",
      "prashna": "मूल्य माँग की लोच परिभाषित करें। माँग वक्रों को चित्रित करें, जिनके माँग की लोच $|e_d| = 0$, $|e_d| = 1$ एवं $|e_d| = \\infty$."
    },
    {
      "id": "long_3",
      "type": "long_answer",
      "chapter_name": "The Theory of the Firm under Perfect Competition",
      "question": "Explain with diagram the Shutdown point of perfect competition firm.",
      "prashna": "पूर्ण प्रतिस्पर्द्धा फर्म के उत्पादन बंदी बिन्दु की सचित्र व्याख्या करें।"
    },
    {
      "id": "long_4",
      "type": "long_answer",
      "chapter_name": "Market Equilibrium",
      "question": "What is price ceiling? Explain with suitable examples.",
      "prashna": "उच्चतम निर्धारित कीमत क्या होती है? उदाहरण के साथ समझायें।"
    },
    {
      "id": "long_5",
      "type": "long_answer",
      "chapter_name": "National Income Accounting",
      "question": "‘$GDP \\equiv$ Aggregate of value added of all firms of the economy.’ Explain with suitable example.",
      "prashna": "‘$GDP \\equiv$ अर्थव्यवस्था के सभी फर्मों के सकल मूल्यवर्धित का कुल योग।’ उदाहरण के साथ व्याख्या करें।"
    },
    {
      "id": "long_6",
      "type": "long_answer",
      "chapter_name": "Money and Banking",
      "question": "Describe the functions of commercial bank.",
      "prashna": "व्यावसायिक बैंक के कार्यों का वर्णन करें।"
    },
    {
      "id": "long_7",
      "type": "long_answer",
      "chapter_name": "Determination of Income and Employment",
      "question": "Prove that the value of Marginal propensity to Consume (MPC) is equal to $1 - MPS$ i.e. $1 - \\text{Marginal Propensity to save}$ in consumption function.",
      "prashna": "सिद्ध करें कि उपभोग फलन के सीमान्त उपभोग प्रवृत्ति (MPC) का मान $1 - MPS$ अर्थात् $1 -$ सीमान्त बचत प्रवृत्ति के बराबर होता है।"
    },
    {
      "id": "long_8",
      "type": "long_answer",
      "chapter_name": "Government Budget and the Economy",
      "question": "What is the relationship between government deficit and government borrowing? Explain.",
      "prashna": "सरकारी घाटे एवं सरकारी ऋण में क्या संबंध है? व्याख्या कीजिए।"
    }
  ]
}